addheader/__init__.py
addheader/add.py
addheader/tests/__init__.py
addheader/tests/test_add.py
addheader-0.3.2.dist-info/LICENSE.md
addheader-0.3.2.dist-info/METADATA
addheader-0.3.2.dist-info/WHEEL
addheader-0.3.2.dist-info/entry_points.txt
addheader-0.3.2.dist-info/top_level.txt
addheader-0.3.2.dist-info/RECORD
