Metadata-Version: 2.1
Name: addheader
Version: 0.3.2
Summary: A command to manage a header section for a source code tree
Author: The IDAES Project
Author-email: Dan Gunter <dkgunter@lbl.gov>
Project-URL: github, https://github.com/idaes/addheader
Project-URL: issues, https://github.com/idaes/addheader/issues
Keywords: software engineering,text processing,utilities
Classifier: Development Status :: 4 - Beta
Classifier: Intended Audience :: End Users/Desktop
Classifier: License :: OSI Approved :: BSD License
Classifier: Natural Language :: English
Classifier: Operating System :: MacOS
Classifier: Operating System :: Microsoft :: Windows
Classifier: Operating System :: Unix
Classifier: Programming Language :: Python
Classifier: Programming Language :: Python :: 3
Classifier: Programming Language :: Python :: 3.7
Classifier: Programming Language :: Python :: 3.8
Classifier: Programming Language :: Python :: 3.9
Classifier: Programming Language :: Python :: Implementation :: CPython
Classifier: Topic :: Software Development :: Libraries :: Python Modules
Classifier: Programming Language :: Python :: 3 :: Only
Requires-Python: >=3.7
License-File: LICENSE.md
Requires-Dist: pyyaml
Provides-Extra: jupyter
Requires-Dist: nbformat ; extra == 'jupyter'
